[
  {
    "question": "พื้นที่ของสามเหลี่ยมด้านเท่าที่มีด้านยาว x คืออะไร?",
    "options": [
      "A = (1/2)x²",
      "A = (√3/4)x²",
      "A = (√3/2)x²",
      "A = x√3"
    ],
    "correct_answer": "A = (√3/4)x²",
    "explanation": "จากตัวอย่าง 3.1.2 พื้นที่ของสามเหลี่ยมด้านเท่า A ที่มีด้านยาว x สามารถคำนวณได้จากสูตร A = (√3/4)x²"
  },
  {
    "question": "สูตรพื้นที่ของวงกลมที่มีรัศมี r คืออะไร?",
    "options": [
      "A = 2πr",
      "A = πr²",
      "A = πd²",
      "A = (1/2)πr²"
    ],
    "correct_answer": "A = πr²",
    "explanation": "จากตัวอย่าง 3.1.3 สูตรพื้นที่ของวงกลมคือ A = πr² โดยที่ r คือรัศมี"
  },
  {
    "question": "ปริมาตรของกรวยกลมตรงที่มีรัศมีฐาน r และความสูง h คืออะไร?",
    "options": [
      "V = πr²h",
      "V = (1/3)πr²h",
      "V = 2πrh",
      "V = (4/3)πr³"
    ],
    "correct_answer": "V = (1/3)πr²h",
    "explanation": "จากตัวอย่าง 3.1.5 ปริมาตรของกรวยกลมตรงคือ V = (1/3)πr²h โดยที่ r คือรัศมีฐาน และ h คือความสูง"
  },
  {
    "question": "ฟังก์ชัน f เป็นฟังก์ชันเพิ่ม (increasing function) บนช่วง (a, b) ถ้าสำหรับทุกค่า a < x1 < x2 < b ข้อใดเป็นจริง?",
    "options": [
      "f(x1) > f(x2)",
      "f(x1) < f(x2)",
      "f'(x) > 0",
      "f'(x) < 0"
    ],
    "correct_answer": "f(x1) < f(x2)",
    "explanation": "จากนิยาม 3.2.1 ฟังก์ชัน f เป็นฟังก์ชันเพิ่มบนช่วง (a, b) ถ้า f(x1) < f(x2) สำหรับทุกค่า a < x1 < x2 < b"
  },
  {
    "question": "ตามทฤษฎีบท 3.2.2 ถ้า f'(x) < 0 สำหรับทุกค่า x ในช่วง (a, b) แล้ว ข้อสรุปใดถูกต้องสำหรับ f?",
    "options": [
      "f เป็นฟังก์ชันเพิ่มบนช่วง (a, b)",
      "f เป็นฟังก์ชันลดบนช่วง (a, b)",
      "f มีค่าสูงสุดสัมพัทธ์",
      "f มีค่าต่ำสุดสัมพัทธ์"
    ],
    "correct_answer": "f เป็นฟังก์ชันลดบนช่วง (a, b)",
    "explanation": "จากทฤษฎีบท 3.2.2 ถ้า f'(x) < 0 สำหรับทุกค่า x ในช่วง (a, b) แล้ว f เป็นฟังก์ชันลดบนช่วง (a, b)"
  },
  {
    "question": "จุด x0 จะถูกเรียกว่าจุดวิกฤต (Critical Point) ของฟังก์ชัน f เมื่อใด?",
    "options": [
      "f'(x0) = 0 เท่านั้น",
      "f'(x0) หาค่าไม่ได้เท่านั้น",
      "f'(x0) = 0 หรือ f'(x0) หาค่าไม่ได้",
      "f''(x0) = 0"
    ],
    "correct_answer": "f'(x0) = 0 หรือ f'(x0) หาค่าไม่ได้",
    "explanation": "จากนิยาม 3.2.5 จุดวิกฤตของฟังก์ชัน f คือจุด x0 ที่ f'(x0) = 0 หรือ f'(x0) หาค่าไม่ได้"
  },
  {
    "question": "ตามทฤษฎีบท 3.2.6 ถ้า f'(x) เปลี่ยนจากเครื่องหมายบวกเป็นลบที่จุดวิกฤต x0 แล้ว f จะมีค่าใดที่ x0?",
    "options": [
      "ค่าต่ำสุดสัมพัทธ์",
      "ค่าสูงสุดสัมพัทธ์",
      "ค่าสูงสุดสัมบูรณ์",
      "ค่าต่ำสุดสัมบูรณ์"
    ],
    "correct_answer": "ค่าสูงสุดสัมพัทธ์",
    "explanation": "จากทฤษฎีบท 3.2.6 ถ้า f'(x) เปลี่ยนจากเครื่องหมายบวกเป็นลบที่จุดวิกฤต x0 แล้ว f จะมีค่าสูงสุดสัมพัทธ์ที่ x0"
  },
  {
    "question": "ตามทฤษฎีบท 3.2.10 (การทดสอบอนุพันธ์อันดับสอง) ถ้า x0 เป็นจุดวิกฤตและ f''(x0) > 0 แล้ว f จะมีค่าใดที่ x0?",
    "options": [
      "ค่าสูงสุดเฉพาะที่",
      "ค่าต่ำสุดเฉพาะที่",
      "ไม่มีค่าสูงสุดหรือต่ำสุด",
      "ต้องใช้การทดสอบอนุพันธ์อันดับหนึ่ง"
    ],
    "correct_answer": "ค่าต่ำสุดเฉพาะที่",
    "explanation": "จากทฤษฎีบท 3.2.10 ถ้า f''(x0) > 0 ที่จุดวิกฤต x0 แล้ว f จะมีค่าต่ำสุดเฉพาะที่ (relative minimum) ที่ x0"
  },
  {
    "question": "สูตรพื้นที่ผิวของกระป๋องรูปทรงกระบอกปิดที่มีรัศมีฐาน r และความสูง h คืออะไร?",
    "options": [
      "S = πr² + 2πrh",
      "S = 2πr² + 2πrh",
      "S = πr²h",
      "S = (4/3)πr³"
    ],
    "correct_answer": "S = 2πr² + 2πrh",
    "explanation": "จากตัวอย่าง 3.2.15 พื้นที่ผิวของกระป๋องทรงกระบอกปิดคือ S = 2πr² (พื้นที่ฐานและฝา) + 2πrh (พื้นที่ผิวข้าง)"
  },
  {
    "question": "ตามทฤษฎีบท 3.3.1 (กฎของโลบิตาล) สามารถใช้ได้โดยตรงกับลิมิตของ f(x)/g(x) ในรูปแบบไม่กำหนดใด?",
    "options": [
      "0 * ∞",
      "∞ - ∞",
      "0/0 หรือ ∞/∞",
      "0^0"
    ],
    "correct_answer": "0/0 หรือ ∞/∞",
    "explanation": "จากทฤษฎีบท 3.3.1 กฎของโลบิตาลใช้ได้โดยตรงกับลิมิตในรูปแบบไม่กำหนด 0/0 หรือ ∞/∞"
  },
  {
    "question": "ข้อใดไม่ใช่รูปแบบไม่กำหนด (indeterminate form)?",
    "options": [
      "0/0",
      "∞/∞",
      "0/1",
      "0 * ∞"
    ],
    "correct_answer": "0/1",
    "explanation": "0/1 มีค่าเท่ากับ 0 ซึ่งไม่ใช่รูปแบบไม่กำหนด ในขณะที่ 0/0, ∞/∞ และ 0*∞ เป็นรูปแบบไม่กำหนด"
  },
  {
    "question": "หาก f เป็นฟังก์ชันลด (decreasing function) บนช่วง (a, b) ถ้าสำหรับทุกค่า a < x1 < x2 < b ข้อใดเป็นจริง?",
    "options": [
      "f(x1) < f(x2)",
      "f(x1) = f(x2)",
      "f(x1) > f(x2)",
      "f'(x) > 0"
    ],
    "correct_answer": "f(x1) > f(x2)",
    "explanation": "จากนิยาม 3.2.1 ฟังก์ชัน f เป็นฟังก์ชันลดบนช่วง (a, b) ถ้า f(x1) > f(x2) สำหรับทุกค่า a < x1 < x2 < b"
  }
]